{
    "title": "Sample Form",
    "description": "This is a test form description",
    "elements": [
        { "key": "text", "value": "Long text" },
        { "key": "email", "value": "Email" },
        { "key": "rating", "value": "Rating" },
        { "key": "button", "value": "Button" },
        { "key": "rating", "value": "Rating" },
        { "key": "calc", "value": "Calculation" },
        { "key": "divider", "value": "Divider" },
        { "key": "switch", "value": "Switch" },
        { "key": "input", "value": "Input" },
        { "key": "checkbox", "value": "Checkbox" }
    ]

}